cogmito/__init__.py
cogmito/main.py
cogmito-0.2.5.dist-info/licenses/LICENSE
cogmito-0.2.5.dist-info/METADATA
cogmito-0.2.5.dist-info/WHEEL
cogmito-0.2.5.dist-info/entry_points.txt
cogmito-0.2.5.dist-info/top_level.txt
cogmito-0.2.5.dist-info/RECORD
