Metadata-Version: 2.4
Name: cogmito
Version: 0.2.5
Summary: AI destekli yayın ve otomasyon botu
Author: Aytunç
Classifier: Programming Language :: Python :: 3.9
Classifier: Operating System :: OS Independent
Requires-Python: >=3.9,<3.10
License-File: LICENSE
Requires-Dist: certifi
Requires-Dist: soundcard
Requires-Dist: soundfile
Requires-Dist: mtranslate
Requires-Dist: ollama
Requires-Dist: selenium
Requires-Dist: undetected-chromedriver
Requires-Dist: SpeechRecognition
Requires-Dist: python-telegram-bot
Requires-Dist: nest_asyncio
Dynamic: author
Dynamic: classifier
Dynamic: license-file
Dynamic: requires-dist
Dynamic: requires-python
Dynamic: summary
